ctf_architect/__init__.py
ctf_architect/__main__.py
ctf_architect/constants.py
ctf_architect/version.py
ctf_architect/cli/__init__.py
ctf_architect/cli/__main__.py
ctf_architect/cli/utils.py
ctf_architect/cli/validators.py
ctf_architect/cli/commands/chall/__init__.py
ctf_architect/cli/commands/repo/__init__.py
ctf_architect/cli/commands/repo/compose.py
ctf_architect/cli/commands/repo/config.py
ctf_architect/cli/commands/repo/mapping.py
ctf_architect/cli/commands/repo/stats.py
ctf_architect/cli/ui/_filedialog.py
ctf_architect/cli/ui/components.py
ctf_architect/cli/ui/console.py
ctf_architect/cli/ui/prompts/__init__.py
ctf_architect/cli/ui/prompts/_confirm.py
ctf_architect/cli/ui/prompts/_select.py
ctf_architect/cli/ui/prompts/base.py
ctf_architect/cli/ui/prompts/input.py
ctf_architect/cli/ui/prompts/session.py
ctf_architect/core/challenge.py
ctf_architect/core/compose.py
ctf_architect/core/config.py
ctf_architect/core/exceptions.py
ctf_architect/core/initialize.py
ctf_architect/core/lint.py
ctf_architect/core/port_mapping.py
ctf_architect/core/repo.py
ctf_architect/core/rules.py
ctf_architect/core/stats.py
ctf_architect/models/__init__.py
ctf_architect/models/base.py
ctf_architect/models/challenge.py
ctf_architect/models/ctf_config.py
ctf_architect/models/lint.py
ctf_architect/models/port_mapping.py
ctf_architect-0.1.0a14.dist-info/METADATA
ctf_architect-0.1.0a14.dist-info/WHEEL
ctf_architect-0.1.0a14.dist-info/entry_points.txt
ctf_architect-0.1.0a14.dist-info/licenses/LICENSE
ctf_architect-0.1.0a14.dist-info/RECORD
