Metadata-Version: 2.4
Name: ctf-architect
Version: 0.1.0a14
Summary: A CTF challenge management tool
Author-email: Jus-Codin <70018166+Jus-Codin@users.noreply.github.com>
License-Expression: MIT
License-File: LICENSE
Classifier: Development Status :: 3 - Alpha
Classifier: Intended Audience :: Developers
Classifier: Intended Audience :: Information Technology
Classifier: License :: OSI Approved :: MIT License
Classifier: Operating System :: OS Independent
Classifier: Programming Language :: Python
Classifier: Programming Language :: Python :: 3
Classifier: Programming Language :: Python :: 3 :: Only
Classifier: Programming Language :: Python :: 3.11
Classifier: Programming Language :: Python :: 3.12
Classifier: Programming Language :: Python :: 3.13
Classifier: Topic :: Software Development :: Libraries :: Python Modules
Requires-Python: >=3.11
Requires-Dist: cyclopts>=3.1.2
Requires-Dist: pydantic>=2.10.4
Requires-Dist: pyyaml>=6.0.2
Requires-Dist: readchar>=4.2.1
Requires-Dist: rich>=13.9.4
Requires-Dist: tomlkit>=0.13.2
